__init__.py
bomcheckgui.py
bomcheckgui-2.4.dist-info/licenses/LICENSE.txt
bomcheckgui-2.4.dist-info/METADATA
bomcheckgui-2.4.dist-info/WHEEL
bomcheckgui-2.4.dist-info/entry_points.txt
bomcheckgui-2.4.dist-info/top_level.txt
bomcheckgui-2.4.dist-info/RECORD
